aprsd_rich_cli_extension/__init__.py
aprsd_rich_cli_extension/cli_helper.py
aprsd_rich_cli_extension/extension.py
aprsd_rich_cli_extension/log.py
aprsd_rich_cli_extension/utils.py
aprsd_rich_cli_extension/cmds/__init__.py
aprsd_rich_cli_extension/cmds/chat.py
aprsd_rich_cli_extension/cmds/chat.tcss
aprsd_rich_cli_extension/cmds/global.tcss
aprsd_rich_cli_extension/cmds/listen.py
aprsd_rich_cli_extension/cmds/listen.tcss
aprsd_rich_cli_extension/components/__init__.py
aprsd_rich_cli_extension/components/add_chat_screen.py
aprsd_rich_cli_extension/components/base_app.py
aprsd_rich_cli_extension/components/header.py
aprsd_rich_cli_extension/components/help_screen.md
aprsd_rich_cli_extension/components/help_screen.py
aprsd_rich_cli_extension/components/packet_widget.py
aprsd_rich_cli_extension/components/splash_screen.md
aprsd_rich_cli_extension/components/splash_screen.py
aprsd_rich_cli_extension/components/utils.py
aprsd_rich_cli_extension/conf/__init__.py
aprsd_rich_cli_extension/conf/main.py
aprsd_rich_cli_extension/conf/opts.py
aprsd_rich_cli_extension-0.1.1.dist-info/licenses/LICENSE
aprsd_rich_cli_extension-0.1.1.dist-info/METADATA
aprsd_rich_cli_extension-0.1.1.dist-info/WHEEL
aprsd_rich_cli_extension-0.1.1.dist-info/entry_points.txt
aprsd_rich_cli_extension-0.1.1.dist-info/top_level.txt
aprsd_rich_cli_extension-0.1.1.dist-info/RECORD
