Metadata-Version: 2.4
Name: aprsd-rich-cli-extension
Version: 0.1.1
Summary: APRSD Extension to create textual rich CLI versions of aprsd commands
Author-email: "Walter A. Boring IV" <waboring@hemna.com>
Maintainer-email: "Walter A. Boring IV" <waboring@hemna.com>
License: 
Keywords: aprs,aprs-is,aprsd,aprsd-server,aprsd-client,aprsd-socket,aprsd-socket-server,aprsd-socket-client
Classifier: Development Status :: 5 - Production/Stable
Classifier: Environment :: Console
Classifier: Intended Audience :: Developers
Classifier: Intended Audience :: End Users/Desktop
Classifier: Intended Audience :: Information Technology
Classifier: Topic :: Communications :: Ham Radio
Classifier: Topic :: Internet
Classifier: Programming Language :: Python :: 3 :: Only
Classifier: Programming Language :: Python :: 3
Classifier: Programming Language :: Python :: 3.8
Classifier: Programming Language :: Python :: 3.9
Classifier: Programming Language :: Python :: 3.10
Classifier: Programming Language :: Python :: 3.11
Requires-Python: >=3.10
License-File: LICENSE
Requires-Dist: aprsd==4.2.0
Requires-Dist: aprslib==0.7.2
Requires-Dist: attrs==25.3.0
Requires-Dist: ax253==0.1.5.post1
Requires-Dist: bitarray==3.6.1
Requires-Dist: certifi==2025.8.3
Requires-Dist: charset-normalizer==3.4.3
Requires-Dist: click==8.2.1
Requires-Dist: dataclasses-json==0.6.7
Requires-Dist: haversine==2.9.0
Requires-Dist: idna==3.10
Requires-Dist: importlib-metadata==8.7.0
Requires-Dist: kiss3==8.0.0
Requires-Dist: linkify-it-py==2.0.3
Requires-Dist: loguru==0.7.3
Requires-Dist: markdown-it-py==4.0.0
Requires-Dist: marshmallow==3.26.1
Requires-Dist: mdit-py-plugins==0.5.0
Requires-Dist: mdurl==0.1.2
Requires-Dist: mypy-extensions==1.1.0
Requires-Dist: netaddr==1.3.0
Requires-Dist: oslo-config==10.0.0
Requires-Dist: oslo-i18n==6.5.1
Requires-Dist: packaging==25.0
Requires-Dist: pbr==6.1.1
Requires-Dist: platformdirs==4.3.8
Requires-Dist: pluggy==1.6.0
Requires-Dist: pygments==2.19.2
Requires-Dist: pyserial==3.5
Requires-Dist: pyserial-asyncio==0.6
Requires-Dist: pytz==2025.2
Requires-Dist: pyyaml==6.0.2
Requires-Dist: requests==2.32.4
Requires-Dist: rfc3986==2.0.0
Requires-Dist: rich==14.1.0
Requires-Dist: rush==2021.4.0
Requires-Dist: setuptools==80.9.0
Requires-Dist: stevedore==5.4.1
Requires-Dist: textual==5.3.0
Requires-Dist: thesmuggler==1.0.1
Requires-Dist: timeago==1.0.16
Requires-Dist: typing-extensions==4.14.1
Requires-Dist: typing-inspect==0.9.0
Requires-Dist: tzlocal==5.3.1
Requires-Dist: uc-micro-py==1.0.3
Requires-Dist: update-checker==0.18.0
Requires-Dist: urllib3==2.5.0
Requires-Dist: wrapt==1.17.3
Requires-Dist: zipp==3.23.0
Provides-Extra: dev
Requires-Dist: pip; extra == "dev"
Requires-Dist: pip-tools; extra == "dev"
Requires-Dist: bump2version; extra == "dev"
Requires-Dist: wheel; extra == "dev"
Requires-Dist: watchdog; extra == "dev"
Requires-Dist: tox; extra == "dev"
Requires-Dist: Sphinx; extra == "dev"
Requires-Dist: twine; extra == "dev"
Dynamic: license-file
